README.md
setup.py
flask_jwt_login/__init__.py
flask_jwt_login/config.py
flask_jwt_login/jwt_login.py
flask_jwt_login/processing.py
flask_jwt_login.egg-info/PKG-INFO
flask_jwt_login.egg-info/SOURCES.txt
flask_jwt_login.egg-info/dependency_links.txt
flask_jwt_login.egg-info/not-zip-safe
flask_jwt_login.egg-info/requires.txt
flask_jwt_login.egg-info/top_level.txt