Metadata-Version: 1.0
Name: flask-jwt-login
Version: 0.0.5
Summary: Flask extension that helps authentication using JWT
Home-page: https://github.com/JeongUkJae/Flask-JWT-Login
Author: Jeong Ukjae
Author-email: jeongukjae@gmail.com
License: MIT
Platform: UNKNOWN
